DTLhelper/__main__.py
DTLhelper/main.py
DTLhelpTool_Python-1.313.0.dist-info/METADATA
DTLhelpTool_Python-1.313.0.dist-info/WHEEL
DTLhelpTool_Python-1.313.0.dist-info/top_level.txt
DTLhelpTool_Python-1.313.0.dist-info/RECORD
